README.md
setup.py
irispy/__init__.py
irispy.egg-info/PKG-INFO
irispy.egg-info/SOURCES.txt
irispy.egg-info/dependency_links.txt
irispy.egg-info/requires.txt
irispy.egg-info/top_level.txt
irispy/dispatcher/__init__.py
irispy/dispatcher/_status.py
irispy/dispatcher/dispatcher.py
irispy/dispatcher/handler.py
irispy/dispatcher/server.py
irispy/types/__init__.py
irispy/types/base.py
irispy/types/events.py
irispy/types/exceptions.py
irispy/types/methods.py
irispy/types/objects.py
irispy/utils/__init__.py
irispy/utils/const.py
irispy/utils/logger.py
irispy/utils/tools.py