Metadata-Version: 2.1
Name: irispy
Version: 1.2
Summary: Async and fast api wrapper for IrisCallback API
Home-page: https://github.com/zpodushkin/irispy
Author: zpodushkin
License: GPL-3.0
Download-URL: https://github.com/zpodushkin/irispy/archive/1.2.tar.gz
Platform: UNKNOWN
Classifier: Programming Language :: Python :: 3.5
Classifier: Programming Language :: Python :: 3.6
Classifier: Programming Language :: Python :: 3.7
Classifier: Operating System :: OS Independent
